odoo/addons/repair_refurbish_repair_stock_move/README.rst
odoo/addons/repair_refurbish_repair_stock_move/__init__.py
odoo/addons/repair_refurbish_repair_stock_move/__manifest__.py
odoo/addons/repair_refurbish_repair_stock_move/i18n/repair_refurbish_repair_stock_move.pot
odoo/addons/repair_refurbish_repair_stock_move/models/__init__.py
odoo/addons/repair_refurbish_repair_stock_move/models/repair_order.py
odoo/addons/repair_refurbish_repair_stock_move/readme/CONTRIBUTORS.rst
odoo/addons/repair_refurbish_repair_stock_move/readme/DESCRIPTION.rst
odoo/addons/repair_refurbish_repair_stock_move/static/description/icon.png
odoo/addons/repair_refurbish_repair_stock_move/static/description/index.html
odoo/addons/repair_refurbish_repair_stock_move/tests/__init__.py
odoo/addons/repair_refurbish_repair_stock_move/tests/test_repair_refurbish.py
odoo_addon_repair_refurbish_repair_stock_move-15.0.1.0.2.dist-info/METADATA
odoo_addon_repair_refurbish_repair_stock_move-15.0.1.0.2.dist-info/WHEEL
odoo_addon_repair_refurbish_repair_stock_move-15.0.1.0.2.dist-info/top_level.txt
odoo_addon_repair_refurbish_repair_stock_move-15.0.1.0.2.dist-info/RECORD
